pokemondex_jsh/__init__.py
pokemondex_jsh/pokemon.csv
pokemondex_jsh/ramdom_pokemon.py
pokemondex_jsh-1.0.0.dist-info/METADATA
pokemondex_jsh-1.0.0.dist-info/WHEEL
pokemondex_jsh-1.0.0.dist-info/top_level.txt
pokemondex_jsh-1.0.0.dist-info/RECORD
